rlvortex/__init__.py
rlvortex/algs/__init__.py
rlvortex/algs/a2c.py
rlvortex/algs/base_algorithm.py
rlvortex/algs/ppo.py
rlvortex/algs/vpg.py
rlvortex/benchmarks/gym_envs/gym_auto_reset_env_trainers.py
rlvortex/benchmarks/gym_envs/gym_env_replayers.py
rlvortex/benchmarks/gym_envs/gym_env_trainers.py
rlvortex/benchmarks/gym_envs/hyperparams/a2c_params.py
rlvortex/benchmarks/gym_envs/hyperparams/ppo_params.py
rlvortex/benchmarks/gym_envs/hyperparams/vpg_params.py
rlvortex/benchmarks/gym_envs/trained_models/best_ppo_lunarlander_300.pth
rlvortex/benchmarks/gym_envs/trained_models/ppo_cartpole_500.pth
rlvortex/benchmarks/gym_envs/trained_models/ppo_lunarlander_300.pth
rlvortex/benchmarks/gym_envs/trained_models/ppo_lunarlanderc_300.pth
rlvortex/benchmarks/gym_envs/trained_models/ppo_mountaincarc_95.pth
rlvortex/benchmarks/gym_envs/trained_models/ppo_pendulum_-133.pth
rlvortex/collectors/__init__.py
rlvortex/collectors/base_collector.py
rlvortex/collectors/common_collector.py
rlvortex/envs/__init__.py
rlvortex/envs/base_env.py
rlvortex/envs/gym_wrapper/__init__.py
rlvortex/envs/gym_wrapper/gym_envs.py
rlvortex/policy/__init__.py
rlvortex/policy/base_policy.py
rlvortex/policy/ppo_policy.py
rlvortex/policy/quick_build.py
rlvortex/replay_buffer/__init__.py
rlvortex/replay_buffer/base_replay_buffer.py
rlvortex/replay_buffer/episode_replay_buffer.py
rlvortex/replay_buffer/ppo_replay_buffer.py
rlvortex/replay_buffer/transition_replay_buffer.py
rlvortex/trainer/__init__.py
rlvortex/trainer/base_trainer.py
rlvortex/trainer/ppo_trainer.py
rlvortex/utils/__init__.py
rlvortex/utils/trainer_utils.py
rlvortex/utils/vlogger.py
rlvortex-0.0.49.dist-info/LICENSE
rlvortex-0.0.49.dist-info/METADATA
rlvortex-0.0.49.dist-info/WHEEL
rlvortex-0.0.49.dist-info/RECORD
