Metadata-Version: 2.1
Name: rlvortex
Version: 0.0.49
Summary: A reinforcement learning algorithm library
License: GPL-2.0-only
Author: ZhiquanW
Author-email: zhiquan.wzq@gmail.com
Requires-Python: >=3.8,<3.9
Classifier: License :: OSI Approved :: GNU General Public License v2 (GPLv2)
Classifier: Programming Language :: Python :: 3
Classifier: Programming Language :: Python :: 3.8
Classifier: Programming Language :: Python :: 3.10
Classifier: Programming Language :: Python :: 3.9
Requires-Dist: gymnasium[all] (==0.29.1)
Requires-Dist: loguru (>=0.7.1,<0.8.0)
Requires-Dist: numpy (==1.24.4)
Requires-Dist: swig (>=4.1.1,<4.2.0)
Requires-Dist: tensorboard (==2.13.0)
Requires-Dist: torch (>=2.3.1,<2.4.0)
